dynamodbfaker/__init__.py
dynamodbfaker/aws.py
dynamodbfaker/cli.py
dynamodbfaker/config.py
dynamodbfaker/dynamodb.py
dynamodbfaker/dynamodbfaker.py
dynamodbfaker/util.py
dynamodbfaker-1.1.0.dist-info/LICENSE
dynamodbfaker-1.1.0.dist-info/METADATA
dynamodbfaker-1.1.0.dist-info/WHEEL
dynamodbfaker-1.1.0.dist-info/entry_points.txt
dynamodbfaker-1.1.0.dist-info/top_level.txt
dynamodbfaker-1.1.0.dist-info/RECORD
