Metadata-Version: 2.2
Name: dynamodbfaker
Version: 1.1.0
Summary: A Python package to generate and insert fake data for AWS Dynamodb
Author: Necati Arslan
Author-email: necatia@gmail.com
Project-URL: Documentation, https://github.com/necatiarslan/dynamodb-faker/blob/main/README.md
Project-URL: Source, https://github.com/necatiarslan/dynamodb-faker
Classifier: Development Status :: 5 - Production/Stable
Classifier: Intended Audience :: Developers
Classifier: License :: OSI Approved :: Apache Software License
Classifier: Programming Language :: Python
Classifier: Programming Language :: Python :: 3
Classifier: Programming Language :: Python :: 3.7
Classifier: Programming Language :: Python :: 3.8
Classifier: Programming Language :: Python :: 3.9
Classifier: Programming Language :: Python :: 3.10
Classifier: Programming Language :: Python :: 3.11
Classifier: Programming Language :: Python :: 3.12
Classifier: Topic :: Software Development :: Libraries
License-File: LICENSE
Requires-Dist: faker
Requires-Dist: pyyaml
Requires-Dist: boto3
Dynamic: author
Dynamic: author-email
Dynamic: classifier
Dynamic: description
Dynamic: description-content-type
Dynamic: project-url
Dynamic: requires-dist
Dynamic: summary
